{"id":72,"date":"2017-04-11T15:30:07","date_gmt":"2017-04-11T15:30:07","guid":{"rendered":"http://phph.co.uk/alderley-park/?page_id=72"},"modified":"2018-01-18T14:41:52","modified_gmt":"2018-01-18T14:41:52","slug":"the-serpentine","status":"publish","type":"page","link":"http://phph.co.uk/alderley-park/the-serpentine/","title":{"rendered":"The Serpentine"},"content":{"rendered":"<p>The largest of our three developments at <strong>Alderley Park</strong>, the 33 family homes here are bordered to the South by the beautiful body of water originally created by the Stanley family in the 19th century for recreation.</p>\n<p>It’s an idyllic spot; <strong>THE SERPENTINE</strong> stretches for almost a third of a mile, with its overhanging trees and plentiful wildlife&#8230; simply perfect on a lazy summer’s afternoon.</p>\n<p>The homes here have been arranged around mature trees and woodland, and the eclectic collection ranges in size and style from traditional three-bedroomed family properties to impressive six-bedroomed villas overlooking the Serpentine itself and the open countryside beyond.</p>\n","protected":false},"excerpt":{"rendered":"<p>The largest of our three developments at Alderley Park, the 33 family homes here are bordered to the South by the beautiful body of water originally created by the Stanley family in the 19th century for recreation. It’s an idyllic spot; THE SERPENTINE stretches for almost a third of a mile, with its overhanging trees &hellip; </p>\n<p class=\"link-more\"><a href=\"http://phph.co.uk/alderley-park/the-serpentine/\" class=\"more-link\">Continue reading<span class=\"screen-reader-text\"> &#8220;The Serpentine&#8221;</span></a></p>\n","protected":false},"author":2,"featured_media":0,"parent":0,"menu_order":0,"comment_status":"closed","ping_status":"closed","template":"page-templates/alderley-park-site.php","meta":[],"better_featured_image":null,"acf":{"which_site":7,"site_image_gallery":[{"image":{"ID":1517,"id":1517,"title":"New-Serpentine-WEB-BANNER_2","filename":"New-Serpentine-WEB-BANNER_2.jpg","url":"http://phph.co.uk/alderley-park/wp-content/uploads/2017/04/New-Serpentine-WEB-BANNER_2.jpg","alt":"","author":"8","description":"","caption":"","name":"new-serpentine-web-banner_2","date":"2017-11-10 14:39:03","modified":"2017-11-10 14:39:12","mime_type":"image/jpeg","type":"image","icon":"http://phph.co.uk/alderley-park/wp-includes/images/media/default.png","width":1354,"height":638,"sizes":{"thumbnail":"http://phph.co.uk/alderley-park/wp-content/uploads/2017/04/New-Serpentine-WEB-BANNER_2-300x300.jpg","thumbnail-width":300,"thumbnail-height":300,"medium":"http://phph.co.uk/alderley-park/wp-content/uploads/2017/04/New-Serpentine-WEB-BANNER_2-800x377.jpg","medium-width":800,"medium-height":377,"medium_large":"http://phph.co.uk/alderley-park/wp-content/uploads/2017/04/New-Serpentine-WEB-BANNER_2.jpg","medium_large-width":768,"medium_large-height":362,"large":"http://phph.co.uk/alderley-park/wp-content/uploads/2017/04/New-Serpentine-WEB-BANNER_2.jpg","large-width":1280,"large-height":603}}},{"image":{"ID":1232,"id":1232,"title":"The Serpentine Plot 17 HR (A)","filename":"The-Serpentine-Plot-17-HR-A-1.jpg","url":"http://phph.co.uk/alderley-park/wp-content/uploads/2017/04/The-Serpentine-Plot-17-HR-A-1.jpg","alt":"","author":"2","description":"","caption":"","name":"the-serpentine-plot-17-hr-a-2","date":"2017-06-13 09:55:35","modified":"2017-06-13 09:55:44","mime_type":"image/jpeg","type":"image","icon":"http://phph.co.uk/alderley-park/wp-includes/images/media/default.png","width":4000,"height":3000,"sizes":{"thumbnail":"http://phph.co.uk/alderley-park/wp-content/uploads/2017/04/The-Serpentine-Plot-17-HR-A-1-300x300.jpg","thumbnail-width":300,"thumbnail-height":300,"medium":"http://phph.co.uk/alderley-park/wp-content/uploads/2017/04/The-Serpentine-Plot-17-HR-A-1-800x600.jpg","medium-width":800,"medium-height":600,"medium_large":"http://phph.co.uk/alderley-park/wp-content/uploads/2017/04/The-Serpentine-Plot-17-HR-A-1.jpg","medium_large-width":768,"medium_large-height":576,"large":"http://phph.co.uk/alderley-park/wp-content/uploads/2017/04/The-Serpentine-Plot-17-HR-A-1-2000x1500.jpg","large-width":1280,"large-height":960}}},{"image":{"ID":1229,"id":1229,"title":"The Serpentine Plot 7 HR (A)","filename":"The-Serpentine-Plot-7-HR-A-1.jpg","url":"http://phph.co.uk/alderley-park/wp-content/uploads/2017/04/The-Serpentine-Plot-7-HR-A-1.jpg","alt":"","author":"2","description":"","caption":"","name":"the-serpentine-plot-7-hr-a-2","date":"2017-06-13 09:55:10","modified":"2017-06-14 11:32:43","mime_type":"image/jpeg","type":"image","icon":"http://phph.co.uk/alderley-park/wp-includes/images/media/default.png","width":4000,"height":3000,"sizes":{"thumbnail":"http://phph.co.uk/alderley-park/wp-content/uploads/2017/04/The-Serpentine-Plot-7-HR-A-1-300x300.jpg","thumbnail-width":300,"thumbnail-height":300,"medium":"http://phph.co.uk/alderley-park/wp-content/uploads/2017/04/The-Serpentine-Plot-7-HR-A-1-800x600.jpg","medium-width":800,"medium-height":600,"medium_large":"http://phph.co.uk/alderley-park/wp-content/uploads/2017/04/The-Serpentine-Plot-7-HR-A-1.jpg","medium_large-width":768,"medium_large-height":576,"large":"http://phph.co.uk/alderley-park/wp-content/uploads/2017/04/The-Serpentine-Plot-7-HR-A-1-2000x1500.jpg","large-width":1280,"large-height":960}}},{"image":{"ID":1461,"id":1461,"title":"The Serpentine Plot 6 HR (C)","filename":"The-Serpentine-Plot-6-HR-C-1.jpg","url":"http://phph.co.uk/alderley-park/wp-content/uploads/2017/04/The-Serpentine-Plot-6-HR-C-1-e1499168466186.jpg","alt":"","author":"2","description":"","caption":"","name":"the-serpentine-plot-6-hr-c-3","date":"2017-07-04 11:40:27","modified":"2017-07-04 11:41:13","mime_type":"image/jpeg","type":"image","icon":"http://phph.co.uk/alderley-park/wp-includes/images/media/default.png","width":4000,"height":2500,"sizes":{"thumbnail":"http://phph.co.uk/alderley-park/wp-content/uploads/2017/04/The-Serpentine-Plot-6-HR-C-1-e1499168466186-300x300.jpg","thumbnail-width":300,"thumbnail-height":300,"medium":"http://phph.co.uk/alderley-park/wp-content/uploads/2017/04/The-Serpentine-Plot-6-HR-C-1-e1499168466186-800x500.jpg","medium-width":800,"medium-height":500,"medium_large":"http://phph.co.uk/alderley-park/wp-content/uploads/2017/04/The-Serpentine-Plot-6-HR-C-1-e1499168466186-768x480.jpg","medium_large-width":768,"medium_large-height":480,"large":"http://phph.co.uk/alderley-park/wp-content/uploads/2017/04/The-Serpentine-Plot-6-HR-C-1-e1499168466186-2000x1250.jpg","large-width":1280,"large-height":800}}},{"image":{"ID":1231,"id":1231,"title":"The Serpentine Plot 16 HR (A)","filename":"The-Serpentine-Plot-16-HR-A-1.jpg","url":"http://phph.co.uk/alderley-park/wp-content/uploads/2017/04/The-Serpentine-Plot-16-HR-A-1-e1498730689640.jpg","alt":"","author":"2","description":"","caption":"","name":"the-serpentine-plot-16-hr-a-2","date":"2017-06-13 09:55:27","modified":"2017-06-29 10:04:57","mime_type":"image/jpeg","type":"image","icon":"http://phph.co.uk/alderley-park/wp-includes/images/media/default.png","width":4000,"height":2500,"sizes":{"thumbnail":"http://phph.co.uk/alderley-park/wp-content/uploads/2017/04/The-Serpentine-Plot-16-HR-A-1-e1497439910169-300x300.jpg","thumbnail-width":300,"thumbnail-height":300,"medium":"http://phph.co.uk/alderley-park/wp-content/uploads/2017/04/The-Serpentine-Plot-16-HR-A-1-e1498730689640-800x500.jpg","medium-width":800,"medium-height":500,"medium_large":"http://phph.co.uk/alderley-park/wp-content/uploads/2017/04/The-Serpentine-Plot-16-HR-A-1-e1498730689640-768x480.jpg","medium_large-width":768,"medium_large-height":480,"large":"http://phph.co.uk/alderley-park/wp-content/uploads/2017/04/The-Serpentine-Plot-16-HR-A-1-e1498730689640-2000x1250.jpg","large-width":1280,"large-height":800}}}]},"_links":{"self":[{"href":"http://phph.co.uk/alderley-park/wp-json/wp/v2/pages/72"}],"collection":[{"href":"http://phph.co.uk/alderley-park/wp-json/wp/v2/pages"}],"about":[{"href":"http://phph.co.uk/alderley-park/wp-json/wp/v2/types/page"}],"author":[{"embeddable":true,"href":"http://phph.co.uk/alderley-park/wp-json/wp/v2/users/2"}],"replies":[{"embeddable":true,"href":"http://phph.co.uk/alderley-park/wp-json/wp/v2/comments?post=72"}],"version-history":[{"href":"http://phph.co.uk/alderley-park/wp-json/wp/v2/pages/72/revisions"}],"wp:attachment":[{"href":"http://phph.co.uk/alderley-park/wp-json/wp/v2/media?parent=72"}],"curies":[{"name":"wp","href":"https://api.w.org/{rel}","templated":true}]}}